logos_sdk/__init__.py
logos_sdk/big_query/BigQuery.py
logos_sdk/big_query/__init__.py
logos_sdk/logging/LogosLogger.py
logos_sdk/logging/__init__.py
logos_sdk/services/CampaignManager.py
logos_sdk/services/Collabim.py
logos_sdk/services/DV360.py
logos_sdk/services/Facebook.py
logos_sdk/services/GoogleAds.py
logos_sdk/services/GoogleSheets.py
logos_sdk/services/MarketMiner.py
logos_sdk/services/MerchantCenter.py
logos_sdk/services/MicrosoftAdvertising.py
logos_sdk/services/Sklik.py
logos_sdk/services/__init__.py
logos_sdk-0.0.24.dist-info/LICENSE
logos_sdk-0.0.24.dist-info/METADATA
logos_sdk-0.0.24.dist-info/WHEEL
logos_sdk-0.0.24.dist-info/top_level.txt
logos_sdk-0.0.24.dist-info/RECORD
