Metadata-Version: 2.1
Name: logos-sdk
Version: 0.0.24
Summary: SDK for Logos platform
Home-page: https://bitbucket.org/databy/logos-sdk-pip/src/master/
Author: Databy.io
Author-email: admin@proficio.cz
Classifier: Programming Language :: Python :: 3
Classifier: Operating System :: OS Independent
License-File: LICENSE
Requires-Dist: requests
Requires-Dist: google-auth
Requires-Dist: google-cloud-logging
Requires-Dist: google-cloud-bigquery
Requires-Dist: python-dotenv
Requires-Dist: google-api-python-client
Requires-Dist: httplib2
Requires-Dist: pandas
Requires-Dist: db-dtypes
Requires-Dist: numpy
